tslearn/__init__.py
tslearn/.cached_datasets/Trace.npz
tslearn/.cached_datasets/singleTrainTest.csv
tslearn/backend/__init__.py
tslearn/backend/backend.py
tslearn/backend/numpy_backend.py
tslearn/backend/pytorch_backend.py
tslearn/barycenters/__init__.py
tslearn/barycenters/dba.py
tslearn/barycenters/euclidean.py
tslearn/barycenters/softdtw.py
tslearn/barycenters/utils.py
tslearn/bases/__init__.py
tslearn/bases/bases.py
tslearn/clustering/__init__.py
tslearn/clustering/kmeans.py
tslearn/clustering/kshape.py
tslearn/clustering/utils.py
tslearn/datasets/__init__.py
tslearn/datasets/cached.py
tslearn/datasets/datasets.py
tslearn/datasets/ucr_uea.py
tslearn/early_classification/__init__.py
tslearn/early_classification/early_classification.py
tslearn/generators/__init__.py
tslearn/generators/generators.py
tslearn/hdftools/__init__.py
tslearn/hdftools/hdftools.py
tslearn/matrix_profile/__init__.py
tslearn/matrix_profile/matrix_profile.py
tslearn/metrics/__init__.py
tslearn/metrics/ctw.py
tslearn/metrics/cycc.py
tslearn/metrics/cysax.py
tslearn/metrics/dtw_variants.py
tslearn/metrics/frechet.py
tslearn/metrics/sax.py
tslearn/metrics/soft_dtw_fast.py
tslearn/metrics/soft_dtw_loss_pytorch.py
tslearn/metrics/softdtw_variants.py
tslearn/metrics/utils.py
tslearn/neighbors/__init__.py
tslearn/neighbors/neighbors.py
tslearn/neural_network/__init__.py
tslearn/neural_network/neural_network.py
tslearn/piecewise/__init__.py
tslearn/piecewise/piecewise.py
tslearn/preprocessing/__init__.py
tslearn/preprocessing/preprocessing.py
tslearn/shapelets/__init__.py
tslearn/shapelets/shapelets.py
tslearn/svm/__init__.py
tslearn/svm/svm.py
tslearn/utils/__init__.py
tslearn/utils/cast.py
tslearn/utils/utils.py
tslearn-0.7.0.dist-info/licenses/LICENSE
tslearn-0.7.0.dist-info/METADATA
tslearn-0.7.0.dist-info/WHEEL
tslearn-0.7.0.dist-info/top_level.txt
tslearn-0.7.0.dist-info/RECORD
