Metadata-Version: 2.4
Name: tslearn
Version: 0.7.0
Summary: A machine learning toolkit dedicated to time-series data
Author-email: Romain Tavenard <romain.tavenard@univ-rennes2.fr>
License-Expression: BSD-2-Clause
Project-URL: documentation, http://tslearn.readthedocs.io
Project-URL: source, https://github.com/tslearn-team/tslearn
Project-URL: issues, https://github.com/tslearn-team/tslearn/issues
Project-URL: changelog, https://github.com/tslearn-team/tslearn/CHANGELOG.md
Classifier: Intended Audience :: Science/Research
Classifier: Intended Audience :: Developers
Classifier: Operating System :: OS Independent
Classifier: Programming Language :: Python :: 3
Classifier: Topic :: Scientific/Engineering :: Artificial Intelligence
Classifier: Topic :: Software Development :: Libraries
Requires-Python: >=3.10
License-File: LICENSE
Requires-Dist: scikit-learn>=1.4
Requires-Dist: numpy>=1.24.3
Requires-Dist: scipy>=1.10.1
Requires-Dist: numba>=0.58.1
Requires-Dist: joblib>=1.2
Provides-Extra: pytorch
Requires-Dist: torch; extra == "pytorch"
Provides-Extra: tests
Requires-Dist: pytest; extra == "tests"
Requires-Dist: h5py; extra == "tests"
Provides-Extra: docs
Requires-Dist: sphinx; extra == "docs"
Requires-Dist: pydata_sphinx_theme; extra == "docs"
Requires-Dist: sphinx-gallery; extra == "docs"
Requires-Dist: sphinx_copybutton; extra == "docs"
Requires-Dist: numpydoc; extra == "docs"
Requires-Dist: matplotlib; extra == "docs"
Requires-Dist: pypandoc; extra == "docs"
Provides-Extra: all-features
Requires-Dist: torch; extra == "all-features"
Requires-Dist: numpy<2; ("darwin" in sys_platform and "x86_64" in platform_machine) and extra == "all-features"
Requires-Dist: h5py; extra == "all-features"
Requires-Dist: keras<3.12; ("darwin" in sys_platform and "x86_64" in platform_machine) and extra == "all-features"
Requires-Dist: keras; extra == "all-features"
Requires-Dist: cesium; extra == "all-features"
Requires-Dist: pandas; extra == "all-features"
Requires-Dist: stumpy; extra == "all-features"
Dynamic: license-file
